qualmeuip/__init__.py
qualmeuip/cli.py
qualmeuip-0.1.1.dist-info/METADATA
qualmeuip-0.1.1.dist-info/WHEEL
qualmeuip-0.1.1.dist-info/entry_points.txt
qualmeuip-0.1.1.dist-info/RECORD
